FIM/__init__.py
FIM/apriori.py
FIM/association_rules.py
FIM/eclat.py
FIM/fpgrowth.py
FIM/hmine.py
FIM/utils.py
FSM/__init__.py
fimproject-0.0.7.dist-info/LICENSE
fimproject-0.0.7.dist-info/METADATA
fimproject-0.0.7.dist-info/WHEEL
fimproject-0.0.7.dist-info/top_level.txt
fimproject-0.0.7.dist-info/RECORD
