Metadata-Version: 2.1
Name: fimproject
Version: 0.0.7
Summary: Frequent Itemset Mining and Frequent Sequence Mining Algorithms package for ARM
Home-page: https://github.com/fatihsen20/Frequent-Mining-Algorithms
Author: Fatih Sen
Author-email: fatihsen.data@gmail.com
Keywords: FIM,Frequent Itemset Mining,Frequent Sequence Mining,Association Rule Mining,ARM
Classifier: Programming Language :: Python :: 3
Classifier: License :: OSI Approved :: MIT License
Classifier: Operating System :: OS Independent
Requires-Python: >=3.7
License-File: LICENSE
Provides-Extra: numpy
Requires-Dist: numpy ; extra == 'numpy'
Provides-Extra: pandas
Requires-Dist: pandas ; extra == 'pandas'
